regolith/__init__.py
regolith/app.py
regolith/broker.py
regolith/builder.py
regolith/chained_db.py
regolith/classlist.py
regolith/client_manager.py
regolith/commands.py
regolith/credentials.json
regolith/database.xsh
regolith/dates.py
regolith/deploy.py
regolith/emailer.py
regolith/exemplars.json
regolith/fsclient.py
regolith/grader.py
regolith/helper.py
regolith/helper_connect_main.py
regolith/helper_gui_main.py
regolith/interact.py
regolith/main.py
regolith/mongoclient.py
regolith/runcontrol.py
regolith/schemas.json
regolith/schemas.py
regolith/sorters.py
regolith/storage.py
regolith/stylers.py
regolith/tools.py
regolith/validators.py
regolith/version.py
regolith/builders/__init__.py
regolith/builders/activitylogbuilder.py
regolith/builders/appraisalbuilder.py
regolith/builders/basebuilder.py
regolith/builders/beamplanbuilder.py
regolith/builders/coabuilder.py
regolith/builders/cpbuilder.py
regolith/builders/cvbuilder.py
regolith/builders/figurebuilder.py
regolith/builders/formalletterbuilder.py
regolith/builders/gradebuilder.py
regolith/builders/grantreportbuilder.py
regolith/builders/htmlbuilder.py
regolith/builders/internalhtmlbuilder.py
regolith/builders/manuscriptreviewbuilder.py
regolith/builders/postdocadbuilder.py
regolith/builders/preslistbuilder.py
regolith/builders/proposalreviewbuilder.py
regolith/builders/publistbuilder.py
regolith/builders/readinglistsbuilder.py
regolith/builders/reimbursementbuilder.py
regolith/builders/resumebuilder.py
regolith/helpers/__init__.py
regolith/helpers/a_expensehelper.py
regolith/helpers/a_grppub_readlisthelper.py
regolith/helpers/a_manurevhelper.py
regolith/helpers/a_presentationhelper.py
regolith/helpers/a_projectumhelper.py
regolith/helpers/a_proposalhelper.py
regolith/helpers/a_proprevhelper.py
regolith/helpers/a_todohelper.py
regolith/helpers/attestationshelper.py
regolith/helpers/basehelper.py
regolith/helpers/f_todohelper.py
regolith/helpers/hellohelper.py
regolith/helpers/l_abstracthelper.py
regolith-0.9.1.dist-info/AUTHORS.rst
regolith-0.9.1.dist-info/LICENSE.rst
regolith-0.9.1.dist-info/METADATA
regolith-0.9.1.dist-info/WHEEL
regolith-0.9.1.dist-info/top_level.txt
regolith-0.9.1.dist-info/RECORD
