Metadata-Version: 2.1
Name: regolith
Version: 0.9.1
Summary: A research group content management system
Author-email: "Simon J.L. Billinge group" <simon.billinge@gmail.com>, Anthony Scopatz <scopatz@gmail.com>
Maintainer-email: "Simon J.L. Billinge group" <simon.billinge@gmail.com>, Anthony Scopatz <scopatz@gmail.com>
Project-URL: Homepage, https://github.com/regro/regolith/
Project-URL: Issues, https://github.com/regro/regolith/issues
Keywords: content management system
Classifier: Development Status :: 5 - Production/Stable
Classifier: Environment :: Console
Classifier: Intended Audience :: Developers
Classifier: Intended Audience :: Science/Research
Classifier: License :: CC0 1.0 Universal (CC0 1.0) Public Domain Dedication
Classifier: Operating System :: MacOS :: MacOS X
Classifier: Operating System :: Microsoft :: Windows
Classifier: Operating System :: POSIX
Classifier: Operating System :: Unix
Classifier: Programming Language :: Python :: 3.10
Classifier: Programming Language :: Python :: 3.11
Classifier: Programming Language :: Python :: 3.12
Classifier: Topic :: Scientific/Engineering :: Physics
Requires-Python: >=3.10
License-File: LICENSE.rst
License-File: AUTHORS.rst
